brocapclient/BroCapGptClient.py
brocapclient/GetResultTimeouts.py
brocapclient/__init__.py
brocapclient/captchaResult.py
brocapclient/clientOptions.py
brocapclient/exceptions.py
brocapclient/requestController.py
brocapclient/utils.py
brocapclient/version.txt
brocapclient/requests/FoxcaptchaRequest.py
brocapclient/requests/FuncaptchaRequest.py
brocapclient/requests/HcaptchaRequest.py
brocapclient/requests/__init__.py
brocapclient/requests/baseRequest.py
brocapclient/requests/baseRequestWithProxy.py
brocapclient/requests/enums.py
brocapclient/requests/proxy_info.py
brocapclient-1.0.4.dist-info/licenses/LICENSE
brocapclient-1.0.4.dist-info/METADATA
brocapclient-1.0.4.dist-info/WHEEL
brocapclient-1.0.4.dist-info/top_level.txt
brocapclient-1.0.4.dist-info/RECORD
